examples/__init__.py
examples/full.py
examples/results/full_trials.csv
pfevaluator/__init__.py
pfevaluator/closeness.py
pfevaluator/closeness_diversity.py
pfevaluator/distribution.py
pfevaluator/front.py
pfevaluator/pfront.py
pfevaluator/ratio.py
pfevaluator/root.py
pfevaluator/spread.py
pfevaluator/tpfront.py
pfevaluator/volume.py
pfevaluator/support_data/MO-ALO/0/100_50_100-results.csv
pfevaluator/support_data/MO-ALO/1/100_50_100-results.csv
pfevaluator/support_data/MO-ALO/2/100_50_100-results.csv
pfevaluator/support_data/MO-ALO/3/100_50_100-results.csv
pfevaluator/support_data/MO-ALO/4/100_50_100-results.csv
pfevaluator/support_data/MO-ALO/5/100_50_100-results.csv
pfevaluator/support_data/MO-ALO/6/100_50_100-results.csv
pfevaluator/support_data/MO-ALO/7/100_50_100-results.csv
pfevaluator/support_data/MO-ALO/8/100_50_100-results.csv
pfevaluator/support_data/MO-ALO/9/100_50_100-results.csv
pfevaluator/support_data/MO-SSA/0/100_50_100-results.csv
pfevaluator/support_data/MO-SSA/1/100_50_100-results.csv
pfevaluator/support_data/MO-SSA/2/100_50_100-results.csv
pfevaluator/support_data/MO-SSA/3/100_50_100-results.csv
pfevaluator/support_data/MO-SSA/4/100_50_100-results.csv
pfevaluator/support_data/MO-SSA/5/100_50_100-results.csv
pfevaluator/support_data/MO-SSA/6/100_50_100-results.csv
pfevaluator/support_data/MO-SSA/7/100_50_100-results.csv
pfevaluator/support_data/MO-SSA/8/100_50_100-results.csv
pfevaluator/support_data/MO-SSA/9/100_50_100-results.csv
pfevaluator/support_data/NSGA-II/0/100_50_100-results.csv
pfevaluator/support_data/NSGA-II/1/100_50_100-results.csv
pfevaluator/support_data/NSGA-II/2/100_50_100-results.csv
pfevaluator/support_data/NSGA-II/3/100_50_100-results.csv
pfevaluator/support_data/NSGA-II/4/100_50_100-results.csv
pfevaluator/support_data/NSGA-II/5/100_50_100-results.csv
pfevaluator/support_data/NSGA-II/6/100_50_100-results.csv
pfevaluator/support_data/NSGA-II/7/100_50_100-results.csv
pfevaluator/support_data/NSGA-II/8/100_50_100-results.csv
pfevaluator-1.1.0.dist-info/LICENSE
pfevaluator-1.1.0.dist-info/METADATA
pfevaluator-1.1.0.dist-info/WHEEL
pfevaluator-1.1.0.dist-info/top_level.txt
pfevaluator-1.1.0.dist-info/RECORD
