Metadata-Version: 2.1
Name: pfevaluator
Version: 1.1.0
Summary: pfevaluator: A library for evaluating performance metrics of Pareto fronts in multiple/many objective optimization problems
Home-page: https://github.com/thieu1995/pfevaluator
Author: Thieu
Author-email: nguyenthieu2102@gmail.com
License: MIT
Download-URL: https://github.com/thieu1995/pfevaluator/archive/v1.1.0.zip
Platform: UNKNOWN
Classifier: Development Status :: 5 - Production/Stable
Classifier: Intended Audience :: Developers
Classifier: Intended Audience :: Education
Classifier: Intended Audience :: Information Technology
Classifier: Intended Audience :: Science/Research
Classifier: License :: OSI Approved :: Apache Software License
Classifier: Natural Language :: English
Classifier: Programming Language :: Python :: 3
Classifier: Programming Language :: Python :: 3.6
Classifier: Programming Language :: Python :: 3.7
Classifier: Programming Language :: Python :: 3.8
Classifier: Topic :: System :: Benchmark
Classifier: Topic :: Scientific/Engineering :: Mathematics
Classifier: Topic :: Scientific/Engineering :: Artificial Intelligence
Classifier: Topic :: Scientific/Engineering :: Information Analysis
Classifier: Topic :: Software Development :: Libraries :: Python Modules
Classifier: Topic :: Utilities
Requires-Python: >=3.6
Requires-Dist: numpy (>=1.18.1)
Requires-Dist: pygmo (>=2.13.0)
